{
  "Name": "Windows.Win32.System.SetupAndMigration",
  "Assembly": "",
  "Types": [
    {
      "Kind": "FunctionPointerType",
      "Parameters": [
        {
          "Name": "CallbackContext",
          "Type": {
            "Kind": "PointerType",
            "Type": "Void"
          },
          "Attributes": [
            "None",
            "In",
            "Optional"
          ]
        }
      ],
      "Name": "OOBE_COMPLETED_CALLBACK",
      "Attributes": [
        "NotPublic",
        "Public",
        "Sealed",
        "AutoClass",
        "BeforeFieldInit"
      ]
    },
    {
      "Kind": "ObjectType",
      "Methods": [
        {
          "Parameters": [
            {
              "Name": "isOOBEComplete",
              "Type": {
                "Kind": "PointerType",
                "Namespace": "Windows.Win32.Foundation",
                "Type": "BOOL"
              },
              "Attributes": [
                "None",
                "Out"
              ]
            }
          ],
          "MethodAttributes": [
            "PrivateScope",
            "FamANDAssem",
            "Family",
            "Public",
            "Static",
            "HideBySig",
            "PinvokeImpl"
          ],
          "ImportAttributes": [
            "None",
            "ExactSpelling",
            "SetLastError",
            "CallingConventionWinApi"
          ],
          "ImplAttributes": [
            "IL"
          ],
          "Name": "OOBEComplete",
          "CustomAttributes": [
            {
              "Name": "Windows.Win32.Foundation.Metadata.DocumentationAttribute",
              "FixedParameters": [
                "https://learn.microsoft.com/windows/win32/api/oobenotification/nf-oobenotification-oobecomplete"
              ]
            }
          ]
        },
        {
          "Parameters": [
            {
              "Name": "OOBECompletedCallback",
              "Type": {
                "Kind": "FunctionPointerType",
                "Namespace": "Windows.Win32.System.SetupAndMigration",
                "Type": "OOBE_COMPLETED_CALLBACK"
              },
              "Attributes": [
                "None",
                "In"
              ]
            },
            {
              "Name": "CallbackContext",
              "Type": {
                "Kind": "PointerType",
                "Type": "Void"
              },
              "Attributes": [
                "None",
                "In",
                "Optional"
              ]
            },
            {
              "Name": "WaitHandle",
              "Type": {
                "Kind": "PointerType",
                "Type": "Void"
              },
              "Attributes": [
                "None",
                "Out"
              ]
            }
          ],
          "MethodAttributes": [
            "PrivateScope",
            "FamANDAssem",
            "Family",
            "Public",
            "Static",
            "HideBySig",
            "PinvokeImpl"
          ],
          "ImportAttributes": [
            "None",
            "ExactSpelling",
            "SetLastError",
            "CallingConventionWinApi"
          ],
          "ImplAttributes": [
            "IL"
          ],
          "Name": "RegisterWaitUntilOOBECompleted",
          "CustomAttributes": [
            {
              "Name": "Windows.Win32.Foundation.Metadata.DocumentationAttribute",
              "FixedParameters": [
                "https://learn.microsoft.com/windows/win32/api/oobenotification/nf-oobenotification-registerwaituntiloobecompleted"
              ]
            }
          ]
        },
        {
          "Parameters": [
            {
              "Name": "WaitHandle",
              "Type": {
                "Kind": "PointerType",
                "Type": "Void"
              },
              "Attributes": [
                "None",
                "In"
              ]
            }
          ],
          "MethodAttributes": [
            "PrivateScope",
            "FamANDAssem",
            "Family",
            "Public",
            "Static",
            "HideBySig",
            "PinvokeImpl"
          ],
          "ImportAttributes": [
            "None",
            "ExactSpelling",
            "SetLastError",
            "CallingConventionWinApi"
          ],
          "ImplAttributes": [
            "IL"
          ],
          "Name": "UnregisterWaitUntilOOBECompleted",
          "CustomAttributes": [
            {
              "Name": "Windows.Win32.Foundation.Metadata.DocumentationAttribute",
              "FixedParameters": [
                "https://learn.microsoft.com/windows/win32/api/oobenotification/nf-oobenotification-unregisterwaituntiloobecompleted"
              ]
            }
          ]
        }
      ],
      "Name": "Apis",
      "Attributes": [
        "NotPublic",
        "Public",
        "Abstract",
        "Sealed",
        "AutoClass",
        "BeforeFieldInit"
      ]
    }
  ]
}